{"cameraMode":{"drawMode":0,"name":"Shaded","section":"Shading Mode"},"sceneLighting":true,"audioPlay":false,"sceneViewState":{"m_AlwaysRefresh":false,"showFog":false,"showSkybox":false,"showFlares":false,"showImageEffects":false,"showParticleSystems":false,"showVisualEffectGraphs":false,"m_FxEnabled":true},"in2DMode":false,"pivot":{"x":20.367000579833986,"y":1.0,"z":1.5},"rotation":{"x":-0.12607118487358094,"y":-0.6868534088134766,"z":0.12249847501516342,"w":-0.7053595781326294},"size":0.8660253882408142,"orthographic":false}